LICENSE
README.md
setup.py
pyimagine/__init__.py
pyimagine/aiby.py
pyimagine/constants.py
pyimagine/utils.py
pyimagine.egg-info/PKG-INFO
pyimagine.egg-info/SOURCES.txt
pyimagine.egg-info/dependency_links.txt
pyimagine.egg-info/requires.txt
pyimagine.egg-info/top_level.txt