Metadata-Version: 2.1
Name: pyimagine
Version: 3.3.8
Summary: Python library for AI-powered image manipulation.
Home-page: https://github.com/hyugogirubato/pyimagine
Author: hyugogirubato
Author-email: hyugogirubato@gmail.com
License: GPL-3.0-only
Keywords: art,image,ai,stable-diffusion
Classifier: Development Status :: 5 - Production/Stable
Classifier: Intended Audience :: Developers
Classifier: Intended Audience :: End Users/Desktop
Classifier: Natural Language :: English
Classifier: Operating System :: OS Independent
Classifier: Programming Language :: Python :: 3
Classifier: Programming Language :: Python :: 3.7
Classifier: Programming Language :: Python :: 3.8
Classifier: Programming Language :: Python :: 3.9
Classifier: Programming Language :: Python :: 3.10
Classifier: Topic :: Utilities
Requires-Python: >=3.7
License-File: LICENSE
